nexus/__init__.py
nexus/main.py
nexus/agent/__init__.py
nexus/agent/approval.py
nexus/agent/graph.py
nexus/agent/metrics.py
nexus/agent/modes.py
nexus/agent/nodes.py
nexus/agent/restrictions.py
nexus/agent/state.py
nexus/commands/__init__.py
nexus/commands/base.py
nexus/commands/core.py
nexus/commands/registry.py
nexus/config/__init__.py
nexus/config/prompts.py
nexus/config/settings.py
nexus/tools/__init__.py
nexus/tools/file_ops.py
nexus/tools/mcp.py
nexus/tools/mode.py
nexus/tools/shell.py
nexus/tools/web_search.py
nexus/ui/__init__.py
nexus/ui/cli.py
nexus/ui/console.py
agent_nexus_cli-0.1.31.dist-info/METADATA
agent_nexus_cli-0.1.31.dist-info/WHEEL
agent_nexus_cli-0.1.31.dist-info/entry_points.txt
agent_nexus_cli-0.1.31.dist-info/top_level.txt
agent_nexus_cli-0.1.31.dist-info/RECORD
