Metadata-Version: 2.4
Name: agent-nexus-cli
Version: 0.1.31
Summary: Nexus is an autonomous CLI coding agent powered by LangGraph and MCP. It plans complex tasks, persists context via SQLite, and securely orchestrates tools. Features specialized Architect/Code modes, real-time metrics, and human-in-the-loop safety for production workflows.
Author-email: Rohit Vilas Ingole <rohit.vilas.ingole@gmail.com>
License: # The MIT License
Project-URL: Homepage, https://github.com/datarohit/nexus
Classifier: Programming Language :: Python :: 3
Classifier: License :: OSI Approved :: MIT License
Classifier: Operating System :: OS Independent
Requires-Python: >=3.14.2
Requires-Dist: aiosqlite==0.22.1
Requires-Dist: ddgs==9.10.0
Requires-Dist: httpx==0.28.1
Requires-Dist: langchain==1.2.7
Requires-Dist: langchain-community==0.4.1
Requires-Dist: langchain-core==1.2.7
Requires-Dist: langchain-mcp-adapters==0.2.1
Requires-Dist: langchain-openai==1.1.7
Requires-Dist: langgraph==1.0.7
Requires-Dist: langgraph-checkpoint==4.0.0
Requires-Dist: langgraph-checkpoint-sqlite==3.0.3
Requires-Dist: langgraph-prebuilt==1.0.7
Requires-Dist: langgraph-sdk==0.3.3
Requires-Dist: langsmith==0.6.4
Requires-Dist: mcp==1.25.0
Requires-Dist: openai==2.15.0
Requires-Dist: orjson==3.11.5
Requires-Dist: pathspec==1.0.3
Requires-Dist: pydantic==2.12.5
Requires-Dist: pydantic-core==2.41.5
Requires-Dist: pydantic-settings==2.12.0
Requires-Dist: python-dotenv==1.2.1
Requires-Dist: pyyaml==6.0.3
Requires-Dist: requests==2.32.5
Requires-Dist: rich==14.2.0
Requires-Dist: rich-click==1.9.6
Requires-Dist: sqlalchemy==2.0.46
Requires-Dist: structlog==25.5.0
Requires-Dist: tenacity==9.1.2
Requires-Dist: tiktoken==0.12.0
Provides-Extra: dev
Requires-Dist: isort==7.0.0; extra == "dev"
Requires-Dist: ruff==0.14.14; extra == "dev"
Requires-Dist: ty==0.0.13; extra == "dev"
